xompletions/_xonsh.py
xompletions/cd.py
xompletions/gh.py
xompletions/pip.py
xompletions/rmdir.py
xonsh/__init__.py
xonsh/__main__.py
xonsh/aliases.py
xonsh/ansi_colors.py
xonsh/built_ins.py
xonsh/cli_utils.py
xonsh/codecache.py
xonsh/color_tools.py
xonsh/commands_cache.py
xonsh/completer.py
xonsh/completion_parser_table.py
xonsh/contexts.py
xonsh/dirstack.py
xonsh/environ.py
xonsh/events.py
xonsh/execer.py
xonsh/foreign_shells.py
xonsh/imphooks.py
xonsh/lazyasd.py
xonsh/lazyimps.py
xonsh/lazyjson.py
xonsh/main.py
xonsh/parser.py
xonsh/parser_table.py
xonsh/platform.py
xonsh/pyghooks.py
xonsh/pygments_cache.py
xonsh/shell.py
xonsh/style_tools.py
xonsh/timings.py
xonsh/tools.py
xonsh/tracer.py
xonsh/wizard.py
xonsh/xonfig.py
xonsh/xontribs.py
xonsh/api/__init__.py
xonsh/api/os.py
xonsh/api/subprocess.py
xonsh/completers/__init__.py
xonsh/completers/_aliases.py
xonsh/completers/base.py
xonsh/completers/bash.py
xonsh/completers/bash_completion.py
xonsh/completers/commands.py
xonsh/completers/completer.py
xonsh/completers/dirs.py
xonsh/completers/environment.py
xonsh/completers/imports.py
xonsh/completers/init.py
xonsh/completers/man.py
xonsh/completers/path.py
xonsh/completers/python.py
xonsh/completers/tools.py
xonsh/history/__init__.py
xonsh/history/base.py
xonsh/history/diff_history.py
xonsh/history/dummy.py
xonsh/history/json.py
xonsh/history/main.py
xonsh/history/sqlite.py
xonsh/lib/__init__.py
xonsh/lib/collections.py
xonsh/lib/inspectors.py
xonsh/lib/itertools.py
xonsh/lib/jsonutils.py
xonsh/lib/lazyasd.py
xonsh/lib/lazyimps.py
xonsh/lib/lazyjson.py
xonsh/lib/modules.py
xonsh/lib/openpy.py
xonsh/lib/os.py
xonsh/lib/pretty.py
xonsh/lib/subprocess.py
xonsh/parsers/__init__.py
xonsh/parsers/ast.py
xonsh/parsers/base.py
xonsh/parsers/completion_context.py
xonsh/parsers/context_check.py
xonsh/parsers/fstring_adaptor.py
xonsh/parsers/lexer.py
xonsh/parsers/rd_parser.py
xonsh/parsers/tokenize.py
xonsh/parsers/v310.py
xonsh/parsers/v313.py
xonsh/parsers/v36.py
xonsh-0.22.0.dist-info/licenses/AUTHORS.rst
xonsh-0.22.0.dist-info/METADATA
xonsh-0.22.0.dist-info/WHEEL
xonsh-0.22.0.dist-info/entry_points.txt
xonsh-0.22.0.dist-info/top_level.txt
xonsh-0.22.0.dist-info/RECORD
