Metadata-Version: 2.4
Name: xonsh
Version: 0.22.0
Summary: Python-powered shell. Full-featured and cross-platform.
Author: Anthony Scopatz
Author-email: scopatz@gmail.com
Maintainer: Xonsh Community
Maintainer-email: xonsh@gil.forsyth.dev
License: BSD 2-Clause License
Project-URL: Homepage, https://xon.sh
Project-URL: documentation, https://xon.sh/contents.html
Project-URL: repository, https://github.com/xonsh/xonsh
Project-URL: changelog, https://github.com/xonsh/xonsh/blob/main/CHANGELOG.md
Project-URL: Issue tracker, https://github.com/xonsh/xonsh/issues
Platform: Cross Platform
Requires-Python: >=3.11
License-File: AUTHORS.rst
Provides-Extra: ptk
Requires-Dist: prompt-toolkit>=3.0.29; extra == "ptk"
Requires-Dist: pyperclip; extra == "ptk"
Provides-Extra: pygments
Requires-Dist: pygments>=2.2; extra == "pygments"
Provides-Extra: mac
Requires-Dist: gnureadline; extra == "mac"
Provides-Extra: linux
Requires-Dist: distro; extra == "linux"
Provides-Extra: proctitle
Requires-Dist: setproctitle; extra == "proctitle"
Provides-Extra: full
Requires-Dist: xonsh[ptk,pygments]; extra == "full"
Requires-Dist: distro; platform_system == "Linux" and extra == "full"
Requires-Dist: setproctitle; platform_system == "Windows" and extra == "full"
Requires-Dist: gnureadline; platform_system == "Darwin" and extra == "full"
Requires-Dist: ujson; extra == "full"
Provides-Extra: bestshell
Requires-Dist: prompt-toolkit>=3.0.29; extra == "bestshell"
Requires-Dist: pygments>=2.2; extra == "bestshell"
Provides-Extra: test
Requires-Dist: xonsh[bestshell]; extra == "test"
Requires-Dist: pytest>=7; extra == "test"
Requires-Dist: restructuredtext_lint; extra == "test"
Requires-Dist: pytest-cov; extra == "test"
Requires-Dist: pytest-mock; extra == "test"
Requires-Dist: pytest-timeout; extra == "test"
Requires-Dist: pytest-subprocess; extra == "test"
Requires-Dist: pytest-rerunfailures; extra == "test"
Requires-Dist: prompt-toolkit>=3.0.29; extra == "test"
Requires-Dist: pygments>=2.2; extra == "test"
Requires-Dist: coverage>=5.3.1; extra == "test"
Requires-Dist: pyte>=0.8.0; extra == "test"
Requires-Dist: virtualenv>=20.16.2; extra == "test"
Requires-Dist: requests; extra == "test"
Provides-Extra: dev
Requires-Dist: xonsh[doc,test]; extra == "dev"
Requires-Dist: pre-commit; extra == "dev"
Requires-Dist: re-ver; extra == "dev"
Requires-Dist: tomli; extra == "dev"
Provides-Extra: doc
Requires-Dist: xonsh[bestshell]; extra == "doc"
Requires-Dist: furo; extra == "doc"
Requires-Dist: numpydoc; extra == "doc"
Requires-Dist: sphinx>=3.1; extra == "doc"
Requires-Dist: psutil; extra == "doc"
Requires-Dist: pyzmq; extra == "doc"
Requires-Dist: matplotlib; extra == "doc"
Requires-Dist: tornado; extra == "doc"
Requires-Dist: runthis-sphinxext; extra == "doc"
Requires-Dist: myst-parser; extra == "doc"
Requires-Dist: sphinx-autobuild; extra == "doc"
Requires-Dist: sphinx-prompt; extra == "doc"
Dynamic: license-file
